MANIFEST.in
README.rst
setup.cfg
setup.py
syncano/__init__.py
syncano/connection.py
syncano/exceptions.py
syncano/release_utils.py
syncano/utils.py
syncano.egg-info/PKG-INFO
syncano.egg-info/SOURCES.txt
syncano.egg-info/dependency_links.txt
syncano.egg-info/not-zip-safe
syncano.egg-info/pbr.json
syncano.egg-info/requires.txt
syncano.egg-info/top_level.txt
syncano/models/__init__.py
syncano/models/accounts.py
syncano/models/archetypes.py
syncano/models/backups.py
syncano/models/base.py
syncano/models/billing.py
syncano/models/bulk.py
syncano/models/channels.py
syncano/models/classes.py
syncano/models/custom_response.py
syncano/models/custom_sockets.py
syncano/models/custom_sockets_utils.py
syncano/models/data_views.py
syncano/models/fields.py
syncano/models/geo.py
syncano/models/hosting.py
syncano/models/incentives.py
syncano/models/instances.py
syncano/models/manager.py
syncano/models/manager_mixins.py
syncano/models/mixins.py
syncano/models/options.py
syncano/models/push_notification.py
syncano/models/registry.py
syncano/models/relations.py
syncano/models/traces.py