Metadata-Version: 1.1
Name: syncano
Version: 5.4.6
Summary: Python Library for syncano.com api
Home-page: http://syncano.com
Author: Syncano
Author-email: support@syncano.io
License: UNKNOWN
Platform: UNKNOWN
Classifier: Development Status :: 5 - Production/Stable
Classifier: License :: OSI Approved :: MIT License
Classifier: Programming Language :: Python
Classifier: Programming Language :: Python :: 2.7
Classifier: Programming Language :: Python :: 3.4
